pydantic_factur_x/__init__.py
pydantic_factur_x/factur_x/__init__.py
pydantic_factur_x/factur_x/_nsmaps.py
pydantic_factur_x/factur_x/address.py
pydantic_factur_x/factur_x/code_lists/__init__.py
pydantic_factur_x/factur_x/code_lists/untdid_1001.py
pydantic_factur_x/factur_x/code_lists/untdid_1229.py
pydantic_factur_x/factur_x/code_lists/untdid_1373.py
pydantic_factur_x/factur_x/code_lists/untdid_2379.py
pydantic_factur_x/factur_x/code_lists/untdid_4451.py
pydantic_factur_x/factur_x/code_lists/untdid_4461.py
pydantic_factur_x/factur_x/common.py
pydantic_factur_x/factur_x/contact.py
pydantic_factur_x/factur_x/document_context.py
pydantic_factur_x/factur_x/document_reference.py
pydantic_factur_x/factur_x/exchanged_document.py
pydantic_factur_x/factur_x/root.py
pydantic_factur_x/factur_x/supply_chain_trade_transaction.py
pydantic_factur_x/factur_x/trade_party.py
pydantic_factur_x/order-x/__init__.py
pydantic_factur_x/tests/fixtures/invoice_1.json
pydantic_factur_x/tests/test_facturx_from_json.py
pydantic_factur_x/tests/test_full_orderx_manual.py
pydantic_factur_x-0.2.0.dist-info/METADATA
pydantic_factur_x-0.2.0.dist-info/WHEEL
pydantic_factur_x-0.2.0.dist-info/RECORD
