Metadata-Version: 2.1
Name: pydantic_factur_x
Version: 0.2.0
Summary: Python library for pydantic factur-x bindings
License: MIT
Author: Thomas chiroux
Author-email: thomas@chiroux.org
Requires-Python: >=3.10,<4.0
Classifier: License :: OSI Approved :: MIT License
Classifier: Programming Language :: Python :: 3
Classifier: Programming Language :: Python :: 3.10
Classifier: Programming Language :: Python :: 3.11
Classifier: Programming Language :: Python :: 3.12
Requires-Dist: pydantic-xml[lxml] (>=2.7,<3.0)
